tap_impactradius/__init__.py
tap_impactradius/schemas/actions.json
tap_impactradius/schemas/clicks.json
tap_impactradius/schemas/invoices.json
tap_impactradius-0.1.0.dist-info/LICENSE.md
tap_impactradius-0.1.0.dist-info/METADATA
tap_impactradius-0.1.0.dist-info/WHEEL
tap_impactradius-0.1.0.dist-info/entry_points.txt
tap_impactradius-0.1.0.dist-info/top_level.txt
tap_impactradius-0.1.0.dist-info/RECORD
